mbinary-1.0.35.dist-info/METADATA
mbinary-1.0.35.dist-info/WHEEL
mbinary/__init__.py
mbinary/_lib.cp313-win_amd64.pyd
mbinary/_lib.pyi
mbinary-1.0.35.dist-info/RECORD
