Metadata-Version: 2.4
Name: mbinary
Version: 1.0.35
Classifier: Programming Language :: Rust
Classifier: Programming Language :: Python :: Implementation :: CPython
Classifier: Programming Language :: Python :: Implementation :: PyPy
Summary: A binary encoding library designed for efficient data storage and transportation in trading platforms.
Keywords: midas,binary-encoding,protocol-buffers
Author-email: Anthony Baxter <anthonybaxter819@gmail.com>
License: Apache-2.0
Requires-Python: >=3.8
